faeruniancalendar/__init__.py
faeruniancalendar/converter.py
faeruniancalendar/data/__init__.py
faeruniancalendar/data/common_year.py
faeruniancalendar/data/leap_year.py
faerunian_calendar-0.0.1.dist-info/METADATA
faerunian_calendar-0.0.1.dist-info/WHEEL
faerunian_calendar-0.0.1.dist-info/licenses/LICENSE
faerunian_calendar-0.0.1.dist-info/RECORD
