Metadata-Version: 2.1
Name: faerunian_calendar
Version: 0.0.1
Summary: A Python module for calculating Faerunian date information based on the Gregorian calendar.
Project-URL: Homepage, https://github.com/sebastianbingham/faeruniancalendar-python
Project-URL: Issues, https://github.com/sebastianbingham/faeruniancalendar-python/issues
Project-URL: Repository, https://github.com/sebastianbingham/faeruniancalendar-python.git
Author-email: Sebastian Bingham <sebastian@sebastianbingham.com>
License: ## MIT License
License-File: LICENSE
Keywords: date calculation,faerun,faerunian
Classifier: Development Status :: 3 - Alpha
Classifier: Intended Audience :: Developers
Classifier: License :: OSI Approved :: MIT License
Classifier: Operating System :: OS Independent
Requires-Python: >=3
